blsCode/__init__.py
blsCode/bls_generic.py
blsCode/bls_ktwo.py
blsCode/clean_and_search.py
blsCode/clean_and_search_BACKUP.py
blsCode/fbls.py
blsCode/fbls3.py
blsCode/outlier_detection.py
blsCode/test_fbls3.py
blsCode/yash_bls.py
dave_vkostov-2.1.data/scripts/AbstractMast.py
dave_vkostov-2.1.data/scripts/AbstractMast_TESS.py
dave_vkostov-2.1.data/scripts/AbstractPrfLookup.py
dave_vkostov-2.1.data/scripts/DaveFit.py
dave_vkostov-2.1.data/scripts/ModShift.py
dave_vkostov-2.1.data/scripts/RoboVet.py
dave_vkostov-2.1.data/scripts/arclen.py
dave_vkostov-2.1.data/scripts/c3eg.py
dave_vkostov-2.1.data/scripts/centroid.py
dave_vkostov-2.1.data/scripts/clipboard.py
dave_vkostov-2.1.data/scripts/compare_lightcurves.py
dave_vkostov-2.1.data/scripts/covar.py
dave_vkostov-2.1.data/scripts/daveplot.py
dave_vkostov-2.1.data/scripts/diffimg.py
dave_vkostov-2.1.data/scripts/estimateSnr.py
dave_vkostov-2.1.data/scripts/exporter.py
dave_vkostov-2.1.data/scripts/fastpsffit.py
dave_vkostov-2.1.data/scripts/fergalmain.py
dave_vkostov-2.1.data/scripts/fft.py
dave_vkostov-2.1.data/scripts/fitsDetrendExport.py
dave_vkostov-2.1.data/scripts/gather.py
dave_vkostov-2.1.data/scripts/generate_images.py
dave_vkostov-2.1.data/scripts/kplrfits.py
dave_vkostov-2.1.data/scripts/loadMultipleDetrendings.py
dave_vkostov-2.1.data/scripts/lsf.py
dave_vkostov-2.1.data/scripts/main.py
dave_vkostov-2.1.data/scripts/mastio.py
dave_vkostov-2.1.data/scripts/multiEvent.py
dave_vkostov-2.1.data/scripts/multiPagePlot.py
dave_vkostov-2.1.data/scripts/multipage.py
dave_vkostov-2.1.data/scripts/nca.py
dave_vkostov-2.1.data/scripts/noise.py
dave_vkostov-2.1.data/scripts/oldblsTask.py
dave_vkostov-2.1.data/scripts/outliers.py
dave_vkostov-2.1.data/scripts/parmap.py
dave_vkostov-2.1.data/scripts/pertransitcentroids.py
dave_vkostov-2.1.data/scripts/phot.py
dave_vkostov-2.1.data/scripts/pipeline.py
dave_vkostov-2.1.data/scripts/plateau.py
dave_vkostov-2.1.data/scripts/plateau_BACKUP.py
dave_vkostov-2.1.dist-info/LICENSE
dave_vkostov-2.1.dist-info/METADATA
dave_vkostov-2.1.dist-info/WHEEL
dave_vkostov-2.1.dist-info/top_level.txt
dave_vkostov-2.1.dist-info/RECORD
