Metadata-Version: 2.1
Name: dave-vkostov
Version: 2.1
Summary: DISCOVERY AND VETTING of EXOPLANETS
Home-page: https://github.com/exoplanetvetting/DAVE
Author: V.Kostov
Author-email: veselin.b.kostov@nasa.gov
License: UNKNOWN
Platform: UNKNOWN
Classifier: Programming Language :: Python :: 3
Classifier: License :: OSI Approved :: MIT License
Classifier: Operating System :: Unix
